{"sections":{"hero_section":{"type":"hero-section","settings":{"heading":"We Build Breakthroughs in Tech-Products","span_text":"","discription":"Empowering you to achieve what you want in the best way possible.","btn_text":"Let's Talk","button_link":"","select_image":"shopify:\/\/shop_images\/company.png"}},"development_strategy":{"type":"development-strategy","blocks":{"722fa8dc-959e-473d-8c83-c1e60cbee7b9":{"type":"block","settings":{"custom_background_color":"#f5435d","number":"1","discription":"Putting together the right team"}},"8329e747-f7fc-440d-8ea2-6823f887c2bc":{"type":"block","settings":{"custom_background_color":"#ffb822","number":"2","discription":"Defining the \"BEST\" development process"}},"65a1ae22-4fd6-486c-ad64-d6c24674058a":{"type":"block","settings":{"custom_background_color":"#3e51d7","number":"3","discription":"Making the client feel at home"}}},"block_order":["722fa8dc-959e-473d-8c83-c1e60cbee7b9","8329e747-f7fc-440d-8ea2-6823f887c2bc","65a1ae22-4fd6-486c-ad64-d6c24674058a"],"settings":{"discription":"With years of experience under our dominion, we know that the key to building a successful software agency revolves around 3 essential aspects."}},"team_work":{"type":"team-work","settings":{"heading":"Team work, Makes the dream work","select_image":"shopify:\/\/shop_images\/dream-work-img1.png"}},"experience_section":{"type":"experience","blocks":{"ae77de77-251c-4958-92bf-42e8dce044b1":{"type":"block","settings":{"icon":"icon-cd-custom-software-model-development-2","discription":"Strong team of\n60+ engineers"}},"a89bf9f9-5df9-4372-b77a-aac4e010e648":{"type":"block","settings":{"icon":"icon-cd-web-mobile-app-development","discription":"80+ Web\nProducts Delivered"}},"4ac719be-9cfa-45fc-91de-53fc8030d36d":{"type":"block","settings":{"icon":"icon-cd-delivery","discription":"50+ Rescue\nMissions"}},"9b070289-9fee-4c95-9861-20ac008278ba":{"type":"block","settings":{"icon":"icon-cd-te-client","discription":"Multiple Award\nWinning Products"}}},"block_order":["ae77de77-251c-4958-92bf-42e8dce044b1","a89bf9f9-5df9-4372-b77a-aac4e010e648","4ac719be-9cfa-45fc-91de-53fc8030d36d","9b070289-9fee-4c95-9861-20ac008278ba"],"settings":{"bg-image":"shopify:\/\/shop_images\/ap-t-banner-desk_1.png","heading":"It's been a great few years"}},"165572272046c1bd5c":{"type":"client-section","blocks":{"641bfa11-ab26-4006-b65c-cced203c7d4d":{"type":"block-1","settings":{"image":"shopify:\/\/shop_images\/global-Id-logo.png"}},"b726c2e5-4920-4bd6-90aa-4c35893bb14d":{"type":"block-2","settings":{"image1":"shopify:\/\/shop_images\/heartbeat.png","image2":"shopify:\/\/shop_images\/our-limbik_e815cd1c-7110-418f-8607-8f43e8719a10.png"}},"a95c0141-8c1e-4876-81b8-8ac6c9458ff4":{"type":"block-3","settings":{"image4":"shopify:\/\/shop_images\/astrazeneca-logo.jpg","image5":"shopify:\/\/shop_images\/nielsen.png","image6":"shopify:\/\/shop_images\/our-family-dollar.png"}},"594fe855-fd0e-4cab-a482-b0609d31dfcf":{"type":"block-4","settings":{"image4":"shopify:\/\/shop_images\/our-client-swatfame.jpg","image5":"shopify:\/\/shop_images\/caribbean-airlines-1.png"}},"5e7f034c-1ca8-43c1-bbe8-fffe1a3bd3d6":{"type":"block-5","settings":{"image":"shopify:\/\/shop_images\/our-lsu.png"}}},"block_order":["641bfa11-ab26-4006-b65c-cced203c7d4d","b726c2e5-4920-4bd6-90aa-4c35893bb14d","a95c0141-8c1e-4876-81b8-8ac6c9458ff4","594fe855-fd0e-4cab-a482-b0609d31dfcf","5e7f034c-1ca8-43c1-bbe8-fffe1a3bd3d6"],"settings":{"heading":"Clients","discription":"We have been working with Fortune 500 companies like"}},"our_promise":{"type":"our-promise","blocks":{"cb109cf1-89f6-44f1-afcc-70b6daf4b690":{"type":"block","settings":{"icon":"icon-cd-about-empthy","user_color":"#f5435d","heading":"Empathy","heading_color":"#f5435d","discription":"Bringing the power of empathy to the table"}},"946f99e4-9c27-44d9-b67f-c4a75448b2d5":{"type":"block","settings":{"icon":"icon-cd-about-high-performance","user_color":"#2d8feb","heading":"High Performance","heading_color":"#2d8feb","discription":"Punch above your weight class"}},"5703aa11-6078-4d8f-9e8c-2531853fc1b1":{"type":"block","settings":{"icon":"icon-cd-dedicated-team","user_color":"#f5754d","heading":"Together","heading_color":"#f5754d","discription":"Teamwork makes the dream work"}},"ad8c4935-46e1-4dbd-9cd8-1d4a5c5103d1":{"type":"block","settings":{"icon":"icon-cd-transparency","user_color":"#0abc7f","heading":"Transparency","heading_color":"#0abc7f","discription":"Authenticity is everything"}}},"block_order":["cb109cf1-89f6-44f1-afcc-70b6daf4b690","946f99e4-9c27-44d9-b67f-c4a75448b2d5","5703aa11-6078-4d8f-9e8c-2531853fc1b1","ad8c4935-46e1-4dbd-9cd8-1d4a5c5103d1"],"settings":{"heading":"Our Promise","discription":"The values which we live by"}},"16557227274c71cbb7":{"type":"award-section","blocks":{"d72b1e4a-73c0-4cb3-b252-de4941ff4e71":{"type":"block","settings":{"select_image":"shopify:\/\/shop_images\/top-clutch.png","select_image2":"shopify:\/\/shop_images\/design-work-image-mob.png","image_link":""}},"366cbe24-33ff-4217-a7c8-2a659c122011":{"type":"block","settings":{"select_image":"shopify:\/\/shop_images\/top-software.png","select_image2":"shopify:\/\/shop_images\/top-mobile-app-development-company-badge-1.png","image_link":""}},"4d6ea778-4106-4310-8c17-96567a8a44b7":{"type":"block","settings":{"select_image":"shopify:\/\/shop_images\/cd-new-clutch.png","select_image2":"shopify:\/\/shop_images\/subtract.png","image_link":""}},"948bff85-a057-4029-9fe1-014db4dd7ca2":{"type":"block","settings":{"select_image":"shopify:\/\/shop_images\/fastest-growing-app.png","select_image2":"shopify:\/\/shop_images\/designrush.png","image_link":""}},"d8abdece-50e9-49a4-8018-795b03cbff5b":{"type":"block","settings":{"select_image":"shopify:\/\/shop_images\/software-usa.png","select_image2":"shopify:\/\/shop_images\/itrateco.png","image_link":""}}},"block_order":["d72b1e4a-73c0-4cb3-b252-de4941ff4e71","366cbe24-33ff-4217-a7c8-2a659c122011","4d6ea778-4106-4310-8c17-96567a8a44b7","948bff85-a057-4029-9fe1-014db4dd7ca2","d8abdece-50e9-49a4-8018-795b03cbff5b"],"settings":{"heading":"Awards & Achievements","discription":"We are proud to be recognized as a top service provider by these platforms."}}},"order":["hero_section","development_strategy","team_work","experience_section","165572272046c1bd5c","our_promise","16557227274c71cbb7"]}